README.md
setup.cfg
setup.py
sksofia/__init__.py
sksofia/sofia_sklearn.py
sksofia.egg-info/PKG-INFO
sksofia.egg-info/SOURCES.txt
sksofia.egg-info/dependency_links.txt
sksofia.egg-info/not-zip-safe
sksofia.egg-info/requires.txt
sksofia.egg-info/top_level.txt