Metadata-Version: 1.1
Name: sksofia
Version: 0.1.1
Summary: a scikit learn wrapper for sofiaml
Home-page: https://github.com/jattenberg/sksofia
Author: jattenberg
Author-email: josh@attenberg.org
License: MIT
Download-URL: https://github.com/jattenberg/sksofia/archive/v0.1.1.tar.gz
Platform: UNKNOWN
Classifier: Development Status :: 4 - Beta
Classifier: Intended Audience :: Developers
Classifier: License :: OSI Approved :: MIT License
Classifier: Programming Language :: Python :: 3.6
